openni/__init__.py
openni/_nite2.py
openni/_openni2.py
openni/nite2.py
openni/openni2.py
openni/utils.py
openni-2.3.0.dist-info/DESCRIPTION.rst
openni-2.3.0.dist-info/METADATA
openni-2.3.0.dist-info/RECORD
openni-2.3.0.dist-info/WHEEL
openni-2.3.0.dist-info/metadata.json
openni-2.3.0.dist-info/top_level.txt
