Metadata-Version: 2.0
Name: openni
Version: 2.3.0
Summary: OpenNI2 and NiTE2 python bindings
Home-page: https://github.com/severin-lemaignan/openni-python
Author: PrimeSense Inc, Séverin Lemaignan, Jerome Flesch, Hajime Murao
Author-email: severin.lemaignan@brl.ac.uk
License: MIT
Keywords: PrimeSense,OpenNI,OpenNI2,Natural Interaction,NiTE,NiTE2
Platform: POSIX
Platform: Windows
Classifier: Development Status :: 4 - Beta
Classifier: License :: OSI Approved :: MIT License
Classifier: Operating System :: Microsoft :: Windows
Classifier: Operating System :: POSIX
Classifier: Operating System :: MacOS
Classifier: Programming Language :: Python :: 2.6
Classifier: Programming Language :: Python :: 2.7
Classifier: Programming Language :: Python :: 3
Classifier: Programming Language :: Python :: 3.2
Classifier: Programming Language :: Python :: 3.3
Provides: openni
